<?xml version='1.0' encoding='UTF-8'?>
<package uuid="sycamore-dance">
 <names>
  <name lang="en_US">Dance</name>
 </names>
 <supportedLanguages>
  <language>en_US</language>
 </supportedLanguages>
 <descriptionLanguages>
  <language>en_US</language>
 </descriptionLanguages>
 <contents>
  <behaviorContent path=".">
   <nature>interactive</nature>
   <permissions/>
  </behaviorContent>
  <behaviorContent path="Cotton-Eye Joe">
   <nature>interactive</nature>
   <permissions/>
  </behaviorContent>
  <behaviorContent path="One More Time">
   <nature>interactive</nature>
   <permissions/>
  </behaviorContent>
  <behaviorContent path="Macarena">
   <nature>interactive</nature>
   <permissions/>
  </behaviorContent>
  <behaviorContent path="Ghostbusters">
   <nature>interactive</nature>
   <permissions/>
  </behaviorContent>
  <behaviorContent path="I Gotta Feeling">
   <nature>interactive</nature>
   <permissions/>
  </behaviorContent>
  <behaviorContent path="Happy">
   <nature>interactive</nature>
   <permissions/>
  </behaviorContent>
  <behaviorContent path="Celebration">
   <nature>interactive</nature>
   <permissions/>
  </behaviorContent>
  <behaviorContent path="Titanium">
   <nature>interactive</nature>
   <permissions/>
  </behaviorContent>
 </contents>
</package>
